swh/loader/metadata/__init__.py
swh/loader/metadata/base.py
swh/loader/metadata/cli.py
swh/loader/metadata/gitea.py
swh/loader/metadata/github.py
swh/loader/metadata/journal_client.py
swh/loader/metadata/py.typed
swh/loader/metadata/tests/__init__.py
swh/loader/metadata/tests/test_base.py
swh/loader/metadata/tests/test_cli.py
swh/loader/metadata/tests/test_gitea.py
swh/loader/metadata/tests/test_github.py
swh/loader/metadata/tests/test_journal_client.py
swh/loader/metadata/tests/data/https_api.github.com/repos_jmarlena_linguist
swh/loader/metadata/tests/data/https_api.github.com/repos_octocat_Hello-World
swh/loader/metadata/tests/data/https_api.github.com/repos_octocat_linguist
swh/loader/metadata/tests/data/https_codeberg.org/api_v1_repos_ForgeFed_ForgeFed
swh/loader/metadata/tests/data/https_codeberg.org/api_v1_repos__ZN3val_ForgeFed
swh/loader/metadata/tests/data/https_git.osgeo.org/gitea_api_v1_repos_postgis_postgis-workshops
swh_loader_metadata-1.4.3.dist-info/licenses/AUTHORS
swh_loader_metadata-1.4.3.dist-info/licenses/LICENSE
swh_loader_metadata-1.4.3.dist-info/METADATA
swh_loader_metadata-1.4.3.dist-info/WHEEL
swh_loader_metadata-1.4.3.dist-info/entry_points.txt
swh_loader_metadata-1.4.3.dist-info/top_level.txt
swh_loader_metadata-1.4.3.dist-info/RECORD
